{"stats":{"minecraft:mined":{"minecraft:podzol":1,"minecraft:large_fern":1,"minecraft:stone":4},"minecraft:crafted":{"regions_unexplored:redwood_planks":28,"minecraft:stone_axe":1,"minecraft:stick":8,"minecraft:stone_pickaxe":1,"minecraft:wooden_pickaxe":1},"minecraft:picked_up":{"minecraft:stick":4,"minecraft:crafting_table":1,"minecraft:wheat_seeds":1,"regions_unexplored:redwood_sapling":14,"regions_unexplored:redwood_planks":4,"twigs:twig":16,"minecraft:cobblestone":4,"regions_unexplored:redwood_log":66},"minecraft:custom":{"minecraft:time_since_rest":16603,"minecraft:crouch_one_cm":1023,"minecraft:play_time":16603,"minecraft:sprint_one_cm":8633,"minecraft:damage_taken":120,"minecraft:walk_one_cm":24477,"minecraft:sneak_time":312,"minecraft:jump":115,"minecraft:damage_dealt":6,"minecraft:time_since_death":16603,"minecraft:hex":0,"minecraft:total_world_time":16603,"minecraft:interact_with_crafting_table":4,"minecraft:fall_one_cm":3982,"minecraft:fly_one_cm":15261},"minecraft:used":{"minecraft:stone_axe":34,"minecraft:crafting_table":1,"minecraft:bread":1,"minecraft:wooden_pickaxe":4}},"DataVersion":3465}